mmeval/__init__.py
mmeval/version.py
mmeval/core/__init__.py
mmeval/core/base_metric.py
mmeval/core/dispatcher.py
mmeval/core/dist.py
mmeval/core/dist_backends/__init__.py
mmeval/core/dist_backends/base_backend.py
mmeval/core/dist_backends/mpi4py.py
mmeval/core/dist_backends/non_dist.py
mmeval/core/dist_backends/oneflow_dist.py
mmeval/core/dist_backends/paddle_dist.py
mmeval/core/dist_backends/tf_horovod.py
mmeval/core/dist_backends/torch_cpu.py
mmeval/core/dist_backends/torch_cuda.py
mmeval/extra_data/niqe_pris_params.npz
mmeval/fileio/__init__.py
mmeval/fileio/io.py
mmeval/fileio/parse.py
mmeval/fileio/backends/__init__.py
mmeval/fileio/backends/base.py
mmeval/fileio/backends/http_backend.py
mmeval/fileio/backends/lmdb_backend.py
mmeval/fileio/backends/local_backend.py
mmeval/fileio/backends/memcached_backend.py
mmeval/fileio/backends/petrel_backend.py
mmeval/fileio/backends/registry_utils.py
mmeval/fileio/handlers/__init__.py
mmeval/fileio/handlers/base.py
mmeval/fileio/handlers/json_handler.py
mmeval/fileio/handlers/pickle_handler.py
mmeval/fileio/handlers/registry_utils.py
mmeval/fileio/handlers/yaml_handler.py
mmeval/metrics/__init__.py
mmeval/metrics/accuracy.py
mmeval/metrics/ava_map.py
mmeval/metrics/average_precision.py
mmeval/metrics/bleu.py
mmeval/metrics/char_recall_precision.py
mmeval/metrics/coco_detection.py
mmeval/metrics/connectivity_error.py
mmeval/metrics/dota_map.py
mmeval/metrics/end_point_error.py
mmeval/metrics/f1_score.py
mmeval/metrics/gradient_error.py
mmeval/metrics/hmean_iou.py
mmeval/metrics/keypoint_auc.py
mmeval/metrics/keypoint_epe.py
mmeval/metrics/keypoint_nme.py
mmeval/metrics/mae.py
mmeval/metrics/matting_mse.py
mmeval/metrics/mean_iou.py
mmeval/metrics/mse.py
mmeval/metrics/niqe.py
mmeval/metrics/oid_map.py
mmeval/metrics/pck_accuracy.py
mmeval/metrics/perplexity.py
mmeval/metrics/precision_recall_f1score.py
mmeval/metrics/proposal_recall.py
mmeval/metrics/psnr.py
mmeval/metrics/rouge.py
mmeval/metrics/sad.py
mmeval-0.2.1.dist-info/LICENSE
mmeval-0.2.1.dist-info/METADATA
mmeval-0.2.1.dist-info/WHEEL
mmeval-0.2.1.dist-info/top_level.txt
mmeval-0.2.1.dist-info/RECORD
