Metadata-Version: 2.1
Name: mmeval
Version: 0.2.1
Summary: Evaluation of deep learning models
Home-page: https://github.com/open-mmlab/mmeval
Author: MMEval Authors
Author-email: openmmlab@gmail.com
License: UNKNOWN
Platform: UNKNOWN
Classifier: Development Status :: 4 - Beta
Classifier: License :: OSI Approved :: Apache Software License
Classifier: Operating System :: OS Independent
Classifier: Programming Language :: Python :: 3
Classifier: Programming Language :: Python :: 3.7
Classifier: Programming Language :: Python :: 3.8
Classifier: Programming Language :: Python :: 3.9
Classifier: Topic :: Scientific/Engineering :: Artificial Intelligence
Requires-Python: >=3.6
Requires-Dist: numpy
Requires-Dist: plum-dispatch (<2.0.0)
Requires-Dist: pyyaml
Requires-Dist: rich
Requires-Dist: scipy
Requires-Dist: opencv-python (>=3)
Provides-Extra: all
Requires-Dist: pycocotools ; extra == 'all'
Requires-Dist: shapely ; extra == 'all'
